ldsc2/__init__.py
ldsc2/build_on_baseline.py
ldsc2/download.py
ldsc2/env.py
ldsc2/strat.py
ldsc2-0.1.0.dist-info/LICENSE
ldsc2-0.1.0.dist-info/METADATA
ldsc2-0.1.0.dist-info/WHEEL
ldsc2-0.1.0.dist-info/entry_points.txt
ldsc2-0.1.0.dist-info/top_level.txt
ldsc2-0.1.0.dist-info/RECORD
