Metadata-Version: 2.1
Name: ldsc2
Version: 0.1.0
Summary: Simplify stratified LD score regression
Home-page: https://github.com/anthony-aylward/ldsc2.git
Author: Anthony Aylward
Author-email: aaylward@eng.ucsd.edu
License: UNKNOWN
Platform: UNKNOWN
Classifier: Programming Language :: Python :: 3
Classifier: License :: OSI Approved :: MIT License
Classifier: Operating System :: OS Independent
Requires-Dist: gitpython
